README
setup.py
pyslave/__init__.py
pyslave.egg-info/PKG-INFO
pyslave.egg-info/SOURCES.txt
pyslave.egg-info/dependency_links.txt
pyslave.egg-info/requires.txt
pyslave.egg-info/top_level.txt