Metadata-Version: 1.1
Name: pyslave
Version: 0.0.1
Summary: Send random functions through celery, without having to define the @task.
Home-page: http://packages.python.org/pyslave
Author: Steven Huf
Author-email: huffy7412@gmail.com
License: UNKNOWN
Keywords: celery
Platform: UNKNOWN
Classifier: Development Status :: 1 - Planning
Classifier: License :: Public Domain
